CHANGES.rst
LICENSE
MANIFEST.in
README.rst
requirements.txt
setup.py
wptranslate/__init__.py
wptranslate/cli.py
wptranslate/mediawiki.py
wptranslate/translator.py
wptranslate.egg-info/PKG-INFO
wptranslate.egg-info/SOURCES.txt
wptranslate.egg-info/dependency_links.txt
wptranslate.egg-info/entry_points.txt
wptranslate.egg-info/requires.txt
wptranslate.egg-info/top_level.txt