Metadata-Version: 1.1
Name: wptranslate
Version: 0.1.1
Summary: Wikipedia-based CLI translator
Home-page: https://github.com/bfontaine/wptranslate
Author: Baptiste Fontaine
Author-email: b@ptistefontaine.fr
License: Copyright © 2014 – Baptiste Fontaine
